dfc/__init__.py
dfc-0.0.1.dist-info/METADATA
dfc-0.0.1.dist-info/WHEEL
dfc-0.0.1.dist-info/RECORD
